{"ile_L_c": 29972.0, "fum_c": 83.0, "val_L_c": 91412.0, "xylt_c": 66.0, "met_L_c": 2376.0, "acmp_c": 66.0, "4hpro_LT_c": 535.0, "hxan_c": 709.0, "5oxpro_c": 64722.0, "hdcea_c": 673.0, "lgnc_c": 200.0, "gly_c": 92372.0, "dca_c": 1095.0, "ind3ac_c": 1561.0, "uri_c": 68.0, "4hphac_c": 45.0, "cit_c": 8104.0, "hdca_c": 5663.0, "gln_L_c": 55646.0, "asp_L_c": 2380.0, "C08261_c": 358.0, "glyclt_c": 391.0, "lys_L_c": 36621.0, "glu_L_c": 7415.0, "glcr_c": 34.0, "dtt_c": 16508.0, "4mop_c": 2529.0, "arach_c": 814.0, "etha_c": 281.0, "taur_c": 3319.0, "avite1_c": 52.0, "ttdca_c": 661.0, "glcn_c": 121.0, "ala_B_c": 369.0, "C01601_c": 8175.0, "citr_L_c": 600.0, "hpdca_c": 249.0, "peamn_c": 551.0, "cgly_c": 250.0, "akg_c": 100.0, "his_L_c": 14967.0, "lnlc_c": 369.0, "bz_c": 2850.0, "ethamp_c": 158.0, "oxa_c": 9775.0, "urate_c": 7556.0, "tyr_L_c": 34805.0, "octa_c": 700.0, "trp_L_c": 30510.0, "L2aadp_c": 47.0, "orn_c": 26170.0, "amp_c": 758.0, "lnlnca_c": 83.0, "ins_c": 185.0, "gsn_c": 58.0, "Lcystin_c": 7581.0, "ala_L_c": 130617.0, "Lkynr_c": 142.0, "alltt_c": 69.0, "thrnt_c": 488.0, "HC00319_c": 15776.0, "xan_c": 95.0, "mal_L_c": 119.0, "adpac_c": 281.0, "lthstrl_c": 52.0, "ocdca_c": 45865.0, "sbt_D_c": 589.0, "phe_L_c": 13944.0, "ddca_c": 4874.0, "yvite_c": 72.0, "bhb_c": 202.0, "thr_L_c": 19858.0, "docosac_c": 118.0, "pro_L_c": 68770.0, "ser_L_c": 20966.0}